setup.py
csp_eventlet/__init__.py
csp_eventlet.egg-info/PKG-INFO
csp_eventlet.egg-info/SOURCES.txt
csp_eventlet.egg-info/dependency_links.txt
csp_eventlet.egg-info/requires.txt
csp_eventlet.egg-info/top_level.txt
csp_eventlet.egg-info/zip-safe